LICENSE.txt
README.txt
setup.py
libs3tl/Extract.py
libs3tl/Load.py
libs3tl/Ml.py
libs3tl/Step.py
libs3tl/Transform.py
libs3tl/__init__.py
libs3tl.egg-info/PKG-INFO
libs3tl.egg-info/SOURCES.txt
libs3tl.egg-info/dependency_links.txt
libs3tl.egg-info/requires.txt
libs3tl.egg-info/top_level.txt
libs3tl/connectors/__init__.py
libs3tl/connectors/destination_3TLIPFS/__init__.py
libs3tl/connectors/destination_3TLIPFS/client.py
libs3tl/connectors/destination_IPFS/__init__.py
libs3tl/connectors/destination_IPFS/client.py
libs3tl/connectors/destination_azblob/__init__.py
libs3tl/connectors/destination_azblob/destination.py
libs3tl/connectors/destination_mysql/__init__.py
libs3tl/connectors/destination_mysql/client.py
libs3tl/connectors/destination_postgres/__init__.py
libs3tl/connectors/destination_postgres/client.py
libs3tl/connectors/destination_sftp_json/__init__.py
libs3tl/connectors/destination_sftp_json/client.py
libs3tl/connectors/destination_sftp_json/destination.py
libs3tl/connectors/source_3TLIPFS/__init__.py
libs3tl/connectors/source_3TLIPFS/client.py
libs3tl/connectors/source_IPFS/__init__.py
libs3tl/connectors/source_IPFS/client.py
libs3tl/connectors/source_exchange_rates/__init__.py
libs3tl/connectors/source_exchange_rates/source.py
libs3tl/connectors/source_file/__init__.py
libs3tl/connectors/source_file/client.py
libs3tl/connectors/source_file/source.py
libs3tl/connectors/source_mysql/__init__.py
libs3tl/connectors/source_mysql/client.py
libs3tl/connectors/source_postgres/__init__.py
libs3tl/connectors/source_postgres/client.py