Metadata-Version: 2.1
Name: libs3tl
Version: 0.1.55
Summary: This is a 3TL module for pipeline creation
Home-page: https://3tl.dev
Author: Thinkartha
Author-email: navin.naik@thinkartha.com
License: BSD 2-clause
Platform: UNKNOWN
Classifier: Development Status :: 1 - Planning
Classifier: Intended Audience :: Science/Research
Classifier: License :: OSI Approved :: BSD License
Classifier: Operating System :: POSIX :: Linux
Classifier: Programming Language :: Python :: 3.9
